stv_pytree/__init__.py
stv_pytree/main.py
stv_pytree/core/__init__.py
stv_pytree/core/stv_parse.py
stv_pytree/core/tree.py
stv_pytree/utils/__init__.py
stv_pytree/utils/change_text.py
stv_pytree/utils/colors.py
stv_pytree/utils/lang_utils.py
stv_pytree/utils/lic.py
stv_pytree/utils/utils.py
stv_pytree-0.0.6.dist-info/METADATA
stv_pytree-0.0.6.dist-info/WHEEL
stv_pytree-0.0.6.dist-info/entry_points.txt
stv_pytree-0.0.6.dist-info/top_level.txt
stv_pytree-0.0.6.dist-info/RECORD
