Metadata-Version: 2.4
Name: stv_pytree
Version: 0.0.6
Summary: 文件树生成工具
Author-email: "星灿长风v(StarWindv)" <starwindv.stv@gmail.com>
License: MIT
Project-URL: Homepage, https://github.com/StarWindv/py-tree
Classifier: Programming Language :: Python :: 3
Requires-Python: >=3.7
Requires-Dist: stv_utils
